langchain_bodo/__init__.py
langchain_bodo/agent_toolkits.py
langchain_bodo/prompt.py
langchain_bodo-0.1.0.dist-info/METADATA
langchain_bodo-0.1.0.dist-info/WHEEL
langchain_bodo-0.1.0.dist-info/RECORD
