Metadata-Version: 2.4
Name: langchain-bodo
Version: 0.1.0
Summary: An integration package connecting Bodo and LangChain
License: MIT
Author: Bodo.ai
Requires-Python: >=3.9,<4.0
Classifier: License :: OSI Approved :: MIT License
Classifier: Programming Language :: Python :: 3
Classifier: Programming Language :: Python :: 3.9
Classifier: Programming Language :: Python :: 3.10
Classifier: Programming Language :: Python :: 3.11
Classifier: Programming Language :: Python :: 3.12
Classifier: Programming Language :: Python :: 3.13
Classifier: Programming Language :: Python :: 3.14
Requires-Dist: bodo (>=2025.8.2,<2026.0.0)
Requires-Dist: langchain-core (>=0.3.15,<0.4.0)
Requires-Dist: langchain-experimental (>=0.3.4,<0.4.0)
Requires-Dist: pandas (>=2.3.2,<3.0.0)
Requires-Dist: tabulate (>=0.9.0,<0.10.0)
Project-URL: Repository, https://github.com/langchain-ai/langchain
Project-URL: Release Notes, https://github.com/langchain-ai/langchain/releases?q=tag%3A%22bodo%3D%3D0%22&expanded=true
Project-URL: Source Code, https://github.com/langchain-ai/langchain/tree/master/libs/partners/bodo
